examples/__init__.py
examples/basic_usage.py
unsilence/Unsilence.py
unsilence/__init__.py
unsilence/__main__.py
unsilence/command_line/ChoiceDialog.py
unsilence/command_line/EntryPoint.py
unsilence/command_line/ParseArguments.py
unsilence/command_line/PrettyTimeEstimate.py
unsilence/command_line/TerminalSupport.py
unsilence/command_line/__init__.py
unsilence/lib/__init__.py
unsilence/lib/detect_silence/DetectSilence.py
unsilence/lib/detect_silence/__init__.py
unsilence/lib/intervals/Interval.py
unsilence/lib/intervals/Intervals.py
unsilence/lib/intervals/TimeCalculations.py
unsilence/lib/intervals/__init__.py
unsilence/lib/render_media/MediaRenderer.py
unsilence/lib/render_media/RenderIntervalThread.py
unsilence/lib/render_media/__init__.py
unsilence/lib/tools/__init__.py
unsilence/lib/tools/ffmpeg_version.py
unsilence-1.0.9.dist-info/LICENSE
unsilence-1.0.9.dist-info/METADATA
unsilence-1.0.9.dist-info/WHEEL
unsilence-1.0.9.dist-info/entry_points.txt
unsilence-1.0.9.dist-info/top_level.txt
unsilence-1.0.9.dist-info/RECORD
