Metadata-Version: 2.1
Name: unsilence
Version: 1.0.9
Summary: Remove Silence from Media Files
Home-page: https://github.com/lagmoellertim/unsilence
Author: Tim-Luca Lagmöller
Author-email: mail@lagmoellertim.de
License: MIT License
Classifier: Programming Language :: Python :: 3
Classifier: License :: OSI Approved :: MIT License
Classifier: Operating System :: OS Independent
License-File: LICENSE
Requires-Dist: rich (~=10.10.0)
